LICENSE.txt
README.rst
setup.cfg
setup.py
satang_pro_sdk/__init__.py
satang_pro_sdk/all_request.py
satang_pro_sdk/get_unix_time.py
satang_pro_sdk/satangpro.py
satang_pro_sdk/satangpro_test.py
satang_pro_sdk.egg-info/PKG-INFO
satang_pro_sdk.egg-info/SOURCES.txt
satang_pro_sdk.egg-info/dependency_links.txt
satang_pro_sdk.egg-info/top_level.txt