Metadata-Version: 2.1
Name: satang-pro-sdk
Version: 1.0.2
Summary: Python SDK for Satangpro Open API
Home-page: https://github.com/satang-official/python-sdk
Author: Satangpro
Author-email: platforms@satangcorp.com
License: MIT
Download-URL: https://github.com/satang-official/python-sdk/archive/refs/tags/V1.0.tar.gz
Keywords: Satangpro API,Satangpro,satangpro,Satangpro python
Platform: UNKNOWN
Classifier: Development Status :: 4 - Beta
Classifier: Intended Audience :: Developers
Classifier: Topic :: Software Development :: Libraries :: Python Modules
Classifier: License :: OSI Approved :: MIT License
Classifier: Programming Language :: Python :: 3
Classifier: Programming Language :: Python :: 3.4
Classifier: Programming Language :: Python :: 3.5
Classifier: Programming Language :: Python :: 3.6
Classifier: Programming Language :: Python :: 3.7
Classifier: Programming Language :: Python :: 3.8
Classifier: Programming Language :: Python :: 3.9
Classifier: Programming Language :: Python :: 3.10
Classifier: Programming Language :: Python :: 3.11
Classifier: Programming Language :: Python :: 3.12
License-File: LICENSE.txt
